micropython_hdc1080/__init__.py
micropython_hdc1080/hdc1080.py
micropython_hdc1080/i2c_helpers.py
micropython_hdc1080-0.1.0.dist-info/LICENSE
micropython_hdc1080-0.1.0.dist-info/METADATA
micropython_hdc1080-0.1.0.dist-info/WHEEL
micropython_hdc1080-0.1.0.dist-info/top_level.txt
micropython_hdc1080-0.1.0.dist-info/RECORD
