Metadata-Version: 2.1
Name: micropython-hdc1080
Version: 0.1.0
Summary: MicroPython driver for the TI HDC1080 Temperature and Humidity sensor
Author-email: JDM <xxyx@mailmeto.mozmail.com>
License: MIT
Project-URL: Homepage, https://github.com/jposada202020/MicroPython_HDC1080
Keywords: sensor,micropython,hdc1080,micropython,driver,hdc1080,temperature,humidity,sensor
Classifier: Intended Audience :: Developers
Classifier: Topic :: Software Development :: Libraries
Classifier: Topic :: Software Development :: Embedded Systems
Classifier: Topic :: System :: Hardware
Classifier: License :: OSI Approved :: MIT License
Classifier: Programming Language :: Python :: Implementation :: MicroPython
License-File: LICENSE
